{
  "quizzes": [
    {
      "id": 1,
      "word": "ありがとう",
      "options": [
        "Thank you",
        "Hello",
        "Goodbye",
        "Excuse me"
      ],
      "answer": 1
    },
    {
      "id": 2,
      "word": "猫",
      "options": [
        "Dog",
        "Cat",
        "Bird",
        "Fish"
      ],
      "answer": 1
    },
    {
      "id": 3,
      "word": "おはよう",
      "options": [
        "Good night",
        "Good evening",
        "Good morning",
        "Goodbye"
      ],
      "answer": 2
    },
    {
      "id": 4,
      "word": "水",
      "options": [
        "Water",
        "Fire",
        "Air",
        "Food"
      ],
      "answer": 0
    },
    {
      "id": 5,
      "word": "愛",
      "options": [
        "Dream",
        "Love",
        "Strength",
        "Hope"
      ],
      "answer": 1
    }
  ]
}
